{
    "TW": {
        "startTime": "2018-02-01T00:00:00+08:00",
        "endTime": "2019-01-31T00:00:00+08:00",
        "countdownSec": 86400,
        "bgPic": "http://cdn.17app.co/c6118d8d-da3c-403a-84b6-2cf9da735624.jpg",
        "topLeftPic": "http://cdn.17app.co/12b57702-46ab-42b9-8832-ce3aeeb55d08.png",
        "topRightPic": "http://cdn.17app.co/f294c5c4-990e-4f5f-acf8-b3cae5a8688e.png",
        "markPic": "http://cdn.17app.co/700e9ef1-46db-4e2a-b9b9-037cd43dd84e.jpg",
        "stickerURL": "http://cdn.17app.co/1.png",
        "message": {
            "TW": "限時購點加倍放送，儲越多賺越多",
            "CN": "限时购点加倍放送，储越多赚越多",
            "EN": "Save up to 18%, buy more and earn more",
            "ID": "Beli semakin banyak, semakin untung",
            "JP": "タイムセールでポイントが倍になります。たくさんチャージするとお得です",
            "KR": "최대 18% 할인, 많이 구입하면 더 싸집니다"
        },
        "title": {
            "TW": "限時加碼 快來搶購",
            "CN": "限时加码 快来抢购",
            "EN": "Flash Sale Go",
            "ID": "Diskon Kilat",
            "JP": "タイムセール！急いで下さい",
            "KR": "타임 세일!! 서두르세요"
        },
        "titleTextURL": {
            "TW": "http://cdn.17app.co/1.png",
            "EN": "http://cdn.17app.co/1.png"
        },
        "titleBgURL": {
            "TW": "http://cdn.17app.co/705335f4-e71d-42d1-975f-f21dfcb8d797.png",
            "EN": "http://cdn.17app.co/705335f4-e71d-42d1-975f-f21dfcb8d797.png"
        },
        "descTextURL": {
            "TW": "http://cdn.17app.co/2.png",
            "EN": "http://cdn.17app.co/2.png"
        },
        "descBgURL": {
            "TW": "http://cdn.17app.co/e69fba61-ef96-4c6b-a1e4-8a8393131337.png",
            "EN": "http://cdn.17app.co/e69fba61-ef96-4c6b-a1e4-8a8393131337.png"
        },
        "descLeftBottomURL": {
            "TW": "http://cdn.17app.co/50275397-2377-48c9-a503-dc6eca382a1f.png",
            "EN": "http://cdn.17app.co/50275397-2377-48c9-a503-dc6eca382a1f.png"
        },
        "descRightBottomURL": {
            "TW": "http://cdn.17app.co/21fc274c-12f4-4ffa-a502-46e52e085b1a.png",
            "EN": "http://cdn.17app.co/21fc274c-12f4-4ffa-a502-46e52e085b1a.png"
        },
        "bonus": {
            "media17_points_100": 5,
            "media17_points_500": 30,
            "media17_points_1100": 100,
            "media17_points_2400": 280,
            "media17_points_6500": 1000,
            "media17_points_14000": 2500
        }
    }
}
