[
	{
		"salePrice": 100,
		"bagID": "gift_luckybag_s",
		"content": [
			{
				"giftID":"beautiful",
				"amount":500
			},
			{
				"giftID":"love_you",
				"amount":500
			},
			{
				"giftID":"great",
				"amount":500
			},
			{
				"giftID":"wow",
				"amount":400
			},
			{
				"giftID":"cheerup",
				"amount":400
			},
			{
				"giftID":"hello",
				"amount":400
			},
			{
				"giftID":"missyou",
				"amount":400
			},
			{
				"giftID":"goodnight",
				"amount":400
			},
			{
				"giftID":"socute",
				"amount":400
			},
			{
				"giftID":"bravo",
				"amount":400
			},
			{
				"giftID":"byebye",
				"amount":400
			},
			{
				"giftID":"gift_newyear_cat",
				"amount":400
			},
			{
				"giftID":"flower",
				"amount":400
			},
			{
				"giftID":"loveballoon",
				"amount":400
			},
			{
				"giftID":"mushroom",
				"amount":400
			},
			{
				"giftID":"singing",
				"amount":400
			},
			{
				"giftID":"tomato_c",
				"amount":400
			},
			{
				"giftID":"beer_2",
				"amount":400
			},
			{
				"giftID":"gift_kiss",
				"amount":400
			},
			{
				"giftID":"gift_tasi",
				"amount":400
			},
			{
				"giftID":"heart_curtain",
				"amount":200
			},
			{
				"giftID":"building",
				"amount":200
			},
			{
				"giftID":"duck",
				"amount":200
			},
			{
				"giftID":"arpk",
				"amount":200
			},
			{
				"giftID":"sakura01",
				"amount":100
			},
			{
				"giftID":"juicer",
				"amount":100
			},
			{
				"giftID":"thunder",
				"amount":100
			},
			{
				"giftID":"cat",
				"amount":100
			},
			{
				"giftID":"dog",
				"amount":100
			},
			{
				"giftID":"camp",
				"amount":100
			},
			{
				"giftID":"island",
				"amount":100
			},
			{
				"giftID":"sakura02",
				"amount":50
			},
			{
				"giftID":"fool_01",
				"amount":50
			},
			{
				"giftID":"animal",
				"amount":50
			},
			{
				"giftID":"firework_new",
				"amount":30
			},
			{
				"giftID":"gift_xmas_02",
				"amount":20
			}
		]
	},
	{
		"salePrice": 1000,
		"bagID": "gift_luckybag_m",
		"content": [
			{
				"giftID":"shootin_stars",
				"amount":500
			},
			{
				"giftID":"sakura02",
				"amount":800
			},
			{
				"giftID":"fool_01",
				"amount":500
			},
			{
				"giftID":"picnic",
				"amount":500
			},
			{
				"giftID":"animal",
				"amount":500
			},
			{
				"giftID":"summer",
				"amount":500
			},
			{
				"giftID":"firework_new",
				"amount":500
			},
			{
				"giftID":"gift_winter_1",
				"amount":500
			},
			{
				"giftID":"bubble",
				"amount":500
			},
			{
				"giftID":"lovegif",
				"amount":500
			},
			{
				"giftID":"big_flowers",
				"amount":500
			},
			{
				"giftID":"raining",
				"amount":500
			},
			{
				"giftID":"dinner",
				"amount":600
			},
			{
				"giftID":"gift_1111",
				"amount":600
			},
			{
				"giftID":"gift_xmas_02",
				"amount":600
			},
			{
				"giftID":"dandelion",
				"amount":400
			},
			{
				"giftID":"bee",
				"amount":500
			},
			{
				"giftID":"kiss",
				"amount":200
			},
			{
				"giftID":"saving_all_my_love",
				"amount":100
			},
			{
				"giftID":"overflowing_heart",
				"amount":100
			},
			{
				"giftID":"flower_coin",
				"amount":100
			},
			{
				"giftID":"heart_connon",
				"amount":100
			},
			{
				"giftID":"forest_party",
				"amount":100
			},
			{
				"giftID":"bag",
				"amount":100
			},
			{
				"giftID":"gift_winter_2",
				"amount":50
			},
			{
				"giftID":"falling_for_you",
				"amount":50
			},
			{
				"giftID":"cheering_for_you",
				"amount":50
			},
			{
				"giftID":"gift_xmas_03",
				"amount":30
			},
			{
				"giftID":"ring",
				"amount":20
			}
		]
	},
	{
		"salePrice": 10000,
		"bagID": "gift_luckybag_l",
		"content": [
			{
				"giftID":"falling_for_you",
				"amount":1300
			},
			{
				"giftID":"cheering_for_you",
				"amount":1500
			},
			{
				"giftID":"ring",
				"amount":2000
			},
			{
				"giftID":"gift_car",
				"amount":2000
			},
			{
				"giftID":"gift_11110",
				"amount":1500
			},
			{
				"giftID":"boat",
				"amount":1300
			},
			{
				"giftID":"gift_airplane",
				"amount":100
			},
			{
				"giftID":"gift_rock_02",
				"amount":100
			},
			{
				"giftID":"moon",
				"amount":100
			},
			{
				"giftID":"star_rain",
				"amount":50
			},
			{
				"giftID":"gift_world",
				"amount":30
			},
			{
				"giftID":"gift_universe",
				"amount":20
			}
		]
	},
	{
		"salePrice": 10000,
		"bagID": "gift_big_transport",
		"content": [
			{
				"giftID":"celebrati_on_fireworks",
				"amount":1500
			},
			{
				"giftID":"falling_for_you",
				"amount":1500
			},
			{
				"giftID":"cheering_for_you",
				"amount":1500
			},
			{
				"giftID":"gift_new_year_3",
				"amount":1500
			},
			{
				"giftID":"gift_car",
				"amount":1500
			},
			{
				"giftID":"boat",
				"amount":500
			},
			{
				"giftID":"gift_rock3",
				"amount":500
			},
			{
				"giftID":"gift_xmas_04",
				"amount":500
			},
			{
				"giftID":"gift_golden_car",
				"amount":300
			},
			{
				"giftID":"gift_airplane",
				"amount":300
			},
			{
				"giftID":"gift_ship",
				"amount":200
			},
			{
				"giftID":"gift_rock_02",
				"amount":180
			},
			{
				"giftID":"gift_bigbro_car",
				"amount":20
			}
		]
	},
	{
		"salePrice": 888,
		"bagID": "gift_bag_boat",
		"content": [
			{
				"giftID":"c_500",
				"amount":500
			},
			{
				"giftID":"shootin_stars",
				"amount":500
			},
			{
				"giftID":"a_1000",
				"amount":400
			},
			{
				"giftID":"firework",
				"amount":400
			},
			{
				"giftID":"bouncing_heart",
				"amount":400
			},
			{
				"giftID":"ninja",
				"amount":400
			},
			{
				"giftID":"planet",
				"amount":400
			},
			{
				"giftID":"sakura02",
				"amount":500
			},
			{
				"giftID":"fool_01",
				"amount":400
			},
			{
				"giftID":"picnic",
				"amount":400
			},
			{
				"giftID":"sneeze",
				"amount":400
			},
			{
				"giftID":"animal",
				"amount":400
			},
			{
				"giftID":"ice",
				"amount":400
			},
			{
				"giftID":"summer",
				"amount":400
			},
			{
				"giftID":"firework_new",
				"amount":400
			},
			{
				"giftID":"gift_moon_1",
				"amount":400
			},
			{
				"giftID":"bubble",
				"amount":300
			},
			{
				"giftID":"lovegif",
				"amount":300
			},
			{
				"giftID":"big_flowers",
				"amount":300
			},
			{
				"giftID":"mom_2",
				"amount":300
			},
			{
				"giftID":"raining",
				"amount":300
			},
			{
				"giftID":"dinner",
				"amount":300
			},
			{
				"giftID":"gift_1111",
				"amount":300
			},
			{
				"giftID":"gift_xmas_02",
				"amount":250
			},
			{
				"giftID":"dandelion",
				"amount":50
			},
			{
				"giftID":"hot_air_balloon",
				"amount":50
			},
			{
				"giftID":"bee",
				"amount":50
			},
			{
				"giftID":"kiss",
				"amount":50
			},
			{
				"giftID":"fall_in_love",
				"amount":50
			},
			{
				"giftID":"love",
				"amount":50
			},
			{
				"giftID":"saving_all_my_love",
				"amount":50
			},
			{
				"giftID":"overflowing_heart",
				"amount":50
			},
			{
				"giftID":"flower_coin",
				"amount":50
			},
			{
				"giftID":"heart_connon",
				"amount":50
			},
			{
				"giftID":"forest_party",
				"amount":50
			},
			{
				"giftID":"watch",
				"amount":50
			},
			{
				"giftID":"bag",
				"amount":50
			},
			{
				"giftID":"gift_winter_2",
				"amount":50
			},
			{
				"giftID":"celebrati_on_fireworks",
				"amount":50
			},
			{
				"giftID":"falling_for_you",
				"amount":50
			},
			{
				"giftID":"cheering_for_you",
				"amount":50
			},
			{
				"giftID":"ring",
				"amount":50
			},
			{
				"giftID":"gift_11110",
				"amount":30
			},
			{
				"giftID":"boat",
				"amount":20
			}
		]
	}
]
